flashpack/__init__.py
flashpack/__main__.py
flashpack/commands.py
flashpack/constants.py
flashpack/deserialization.py
flashpack/mixin.py
flashpack/serialization.py
flashpack/utils.py
flashpack/version.py
flashpack/integrations/__init__.py
flashpack/integrations/patch.py
flashpack/integrations/diffusers/__init__.py
flashpack/integrations/diffusers/auto_model.py
flashpack/integrations/diffusers/model.py
flashpack/integrations/diffusers/patch.py
flashpack/integrations/diffusers/pipeline.py
flashpack/integrations/transformers/__init__.py
flashpack/integrations/transformers/model.py
flashpack/integrations/transformers/patch.py
flashpack-0.2.1.dist-info/licenses/LICENSE
flashpack-0.2.1.dist-info/METADATA
flashpack-0.2.1.dist-info/WHEEL
flashpack-0.2.1.dist-info/entry_points.txt
flashpack-0.2.1.dist-info/top_level.txt
flashpack-0.2.1.dist-info/RECORD
