Metadata-Version: 2.4
Name: flashpack
Version: 0.2.1
Summary: Load ML models fast
Author: fal-ai-community
Classifier: Programming Language :: Python :: 3
Classifier: Programming Language :: Python :: 3.10
Classifier: Programming Language :: Python :: 3.11
Classifier: Programming Language :: Python :: 3.12
Classifier: License :: OSI Approved :: MIT License
Classifier: Operating System :: OS Independent
Requires-Python: >=3.10
License-File: LICENSE
Requires-Dist: accelerate>=1.0
Requires-Dist: click>=6.0
Requires-Dist: safetensors>=0.4
Requires-Dist: torch>=2.0
Provides-Extra: dev
Requires-Dist: pytest>=8.4.1; extra == "dev"
Requires-Dist: pre-commit>=3.0.0; extra == "dev"
Requires-Dist: setuptools-scm>=9.2.0; extra == "dev"
Dynamic: license-file
